Metadata-Version: 1.0
Name: setuptools-cython
Version: 0.1
Summary: Cython setuptools integration
Home-page: http://pypi.python.org/pypi/setuptools_cython/
Author: Gabriel de Perthuis
Author-email: gabriel.de-perthuis@c-s.fr
License: http://www.gnu.org/licenses/gpl-2.0.html
Platform: UNKNOWN
Classifier: Framework :: Setuptools Plugin
Classifier: Topic :: Software Development :: Build Tools
